fdadb/__init__.py
fdadb/admin.py
fdadb/api.py
fdadb/api_urls.py
fdadb/es_search.py
fdadb/models.py
fdadb/serializers.py
fdadb/management/__init__.py
fdadb/management/commands/__init__.py
fdadb/management/commands/fdadb_es_index.py
fdadb/management/commands/fetch_ndc_database.py
fdadb/migrations/0001_initial.py
fdadb/migrations/0002_auto_20190904_1512.py
fdadb/migrations/__init__.py
fdadb-0.2.0.dist-info/AUTHORS
fdadb-0.2.0.dist-info/LICENSE
fdadb-0.2.0.dist-info/METADATA
fdadb-0.2.0.dist-info/WHEEL
fdadb-0.2.0.dist-info/top_level.txt
fdadb-0.2.0.dist-info/RECORD
