Metadata-Version: 2.1
Name: fdadb
Version: 0.2.0
Summary: FDA Drug Database
Home-page: https://github.com/HealthByRo/fdadb
Author: Michal Proszek
Author-email: michal.proszek@gmail.com
License: MIT
Classifier: Development Status :: 3 - Alpha
Classifier: Environment :: Web Environment
Classifier: Framework :: Django
Classifier: Intended Audience :: Developers
Classifier: Operating System :: OS Independent
Classifier: Programming Language :: Python
Classifier: Programming Language :: Python :: 3.9
Classifier: Programming Language :: Python :: 3.10
Classifier: Programming Language :: Python :: 3.11
Classifier: Topic :: Internet :: WWW/HTTP
License-File: LICENSE
License-File: AUTHORS
Requires-Dist: djangorestframework >=3.6.0
Requires-Dist: django-extensions >=2.1.3
Requires-Dist: drf-tweaks >=0.8.0
Requires-Dist: elasticsearch >=6.3.1
Requires-Dist: requests >=2.20.1
